topsis/__init__.py
topsis/topsis.py
topsis_pratham_102303052-1.0.2.dist-info/licenses/LICENCE
topsis_pratham_102303052-1.0.2.dist-info/METADATA
topsis_pratham_102303052-1.0.2.dist-info/WHEEL
topsis_pratham_102303052-1.0.2.dist-info/entry_points.txt
topsis_pratham_102303052-1.0.2.dist-info/top_level.txt
topsis_pratham_102303052-1.0.2.dist-info/RECORD
