Metadata-Version: 2.4
Name: Topsis-Pratham-102303052
Version: 1.0.2
Summary: A Python package for TOPSIS (Technique for Order of Preference by Similarity to Ideal Solution) analysis
Home-page: https://github.com/prathamgarg/Topsis-Pratham-102303052
Author: Pratham Garg
Author-email: pgarg7_be23@thapar.edu
Classifier: Programming Language :: Python :: 3
Classifier: License :: OSI Approved :: MIT License
Classifier: Operating System :: OS Independent
Requires-Python: >=3.6
License-File: LICENCE
Requires-Dist: pandas>=1.0.0
Requires-Dist: numpy>=1.18.0
Dynamic: author
Dynamic: author-email
Dynamic: classifier
Dynamic: description
Dynamic: description-content-type
Dynamic: home-page
Dynamic: license-file
Dynamic: requires-dist
Dynamic: requires-python
Dynamic: summary
